lingo_api/__init__.py
lingo_api/const.py
lingo_api/lingo.cp39-win_amd64.pyd
lingo_api/lingoExceptions.py
lingo_api/loadLibs.py
lingo_api/modelLoader.py
lingo_api/pyLingo.c
lingo_test/__init__.py
lingo_test/__main__.py
lingo_api-21.0.11.dist-info/METADATA
lingo_api-21.0.11.dist-info/WHEEL
lingo_api-21.0.11.dist-info/top_level.txt
lingo_api-21.0.11.dist-info/RECORD
