Metadata-Version: 2.1
Name: lingo-api
Version: 21.0.11
Summary: Python interface to LINGO API
Home-page: http://www.lindo.com
Author: Lindo Systems, Inc.
Author-email: support@lindo.com
License: UNKNOWN
Platform: Windows, Linux
Classifier: Programming Language :: Python :: 3
Classifier: Programming Language :: Python :: 3.7
Classifier: Programming Language :: Python :: 3.8
Classifier: Programming Language :: Python :: 3.9
Classifier: Programming Language :: Python :: 3.10
Classifier: Programming Language :: Python :: 3 :: Only
Requires-Python: >=3.7
Requires-Dist: numpy
Requires-Dist: pandas
